intake_informaticslab/__init__.py
intake_informaticslab/_version.py
intake_informaticslab/cats/air_quality_cat.yaml
intake_informaticslab/cats/mogreps_cat.yaml
intake_informaticslab/cats/ukv_timeseries_cat.yaml
intake_informaticslab/cats/mogreps_g/depth_level_data.yaml
intake_informaticslab/cats/mogreps_g/height_level_data.yaml
intake_informaticslab/cats/mogreps_g/pressure_level_data.yaml
intake_informaticslab/cats/mogreps_g/single_level_data.yaml
intake_informaticslab/cats/mogreps_uk/depth_level_data.yaml
intake_informaticslab/cats/mogreps_uk/height_level_data.yaml
intake_informaticslab/cats/mogreps_uk/pressure_level_data.yaml
intake_informaticslab/cats/mogreps_uk/single_level_data.yaml
intake_informaticslab/datasources/__init__.py
intake_informaticslab/datasources/aq_datasource.py
intake_informaticslab/datasources/dataset.py
intake_informaticslab/datasources/utils.py
intake_informaticslab/zarrhypothetic/__init__.py
intake_informaticslab/zarrhypothetic/zarrhypothetic.py
intake_informaticslab-0.0.18.dist-info/LICENSE
intake_informaticslab-0.0.18.dist-info/METADATA
intake_informaticslab-0.0.18.dist-info/WHEEL
intake_informaticslab-0.0.18.dist-info/entry_points.txt
intake_informaticslab-0.0.18.dist-info/top_level.txt
intake_informaticslab-0.0.18.dist-info/zip-safe
intake_informaticslab-0.0.18.dist-info/RECORD
