Metadata-Version: 2.1
Name: intake-informaticslab
Version: 0.0.18
Summary: Intake catalogues and associated drivers providing access to hundreds of terabytes of Met Office data.
Home-page: https://github.com/informatics-lab/intake_informaticslab
Author: Theo McCaie
Author-email: theo.mccaie@informaticslab.co.uk
License: UNKNOWN
Platform: UNKNOWN
Classifier: Operating System :: OS Independent
Classifier: Programming Language :: Python
Classifier: Programming Language :: Python :: 3
Classifier: Programming Language :: Python :: 3.6
Classifier: Programming Language :: Python :: 3.7
Classifier: Programming Language :: Python :: 3.8
Classifier: Topic :: Software Development :: Libraries :: Python Modules
Classifier: Natural Language :: English
Requires-Dist: numpy (>=1.11)
Requires-Dist: dask (>=1.0)
Requires-Dist: xarray
Requires-Dist: zarr (>=2)
Requires-Dist: adlfs (>=0.5.9)
Requires-Dist: h5netcdf (>=0.8)
Requires-Dist: intake
Requires-Dist: intake-xarray
Requires-Dist: toolz
